aiohttp_clean_jwt/__init__.py
aiohttp_clean_jwt/middleware.py
aiohttp_clean_jwt-0.1.1.dist-info/LICENSE
aiohttp_clean_jwt-0.1.1.dist-info/METADATA
aiohttp_clean_jwt-0.1.1.dist-info/WHEEL
aiohttp_clean_jwt-0.1.1.dist-info/top_level.txt
aiohttp_clean_jwt-0.1.1.dist-info/RECORD
