Metadata-Version: 2.1
Name: aiohttp_clean_jwt
Version: 0.1.1
Summary: jwt authentication for aiohttp
Home-page: https://gitflic.ru/project/vlakir/aiohttp-clean-jwt.git
Author: Vladimir Kirievskiy
Author-email: vladimir@kirievskiy.ru
Classifier: Programming Language :: Python :: 3.8
Classifier: License :: OSI Approved :: GNU General Public License v3 (GPLv3)
Classifier: Topic :: Scientific/Engineering
License-File: LICENSE
